strainpycon/__init__.py
strainpycon/integration.py
strainpycon/psimplex.py
strainpycon/recon.py
strainpycon/utils.py
strainpycon-1.0.dist-info/METADATA
strainpycon-1.0.dist-info/RECORD
strainpycon-1.0.dist-info/WHEEL
strainpycon-1.0.dist-info/top_level.txt
strainpycon-1.0.egg-info/PKG-INFO
strainpycon-1.0.egg-info/SOURCES.txt
strainpycon-1.0.egg-info/dependency_links.txt
strainpycon-1.0.egg-info/top_level.txt
