Metadata-Version: 2.1
Name: strainpycon
Version: 1.0
Summary: Strain disambiguation methods for mixed DNA samples
Home-page: https://www.ymsir.com/strainpycon/
Author: Ymir Vigfusson, Lars Ruthotto, Rebecca M. Mitchell, Lauri Mustonen, Xiangxi Gao
Author-email: ymir.vigfusson@emory.edu
License: UNKNOWN
Platform: UNKNOWN
Classifier: Programming Language :: Python :: 3
Classifier: License :: OSI Approved :: MIT License
Classifier: Operating System :: OS Independent
